pupyl/__init__.py
pupyl/cli.py
pupyl/search.py
pupyl/verbosity.py
pupyl/addendum/__init__.py
pupyl/addendum/operators.py
pupyl/duplex/__init__.py
pupyl/duplex/exceptions.py
pupyl/duplex/file_io.py
pupyl/duplex/file_types.py
pupyl/duplex/image.py
pupyl/embeddings/__init__.py
pupyl/embeddings/exceptions.py
pupyl/embeddings/features.py
pupyl/indexer/__init__.py
pupyl/indexer/exceptions.py
pupyl/indexer/facets.py
pupyl/storage/__init__.py
pupyl/storage/database.py
pupyl/web/__init__.py
pupyl/web/interface.py
pupyl-0.14.7.dist-info/LICENSE
pupyl-0.14.7.dist-info/METADATA
pupyl-0.14.7.dist-info/WHEEL
pupyl-0.14.7.dist-info/entry_points.txt
pupyl-0.14.7.dist-info/top_level.txt
pupyl-0.14.7.dist-info/RECORD
