Metadata-Version: 2.1
Name: pupyl
Version: 0.14.7
Summary: 🧿 Pupyl is a really fast image search library which you can index your own (millions of) images and find similar images in millisecond.
Home-page: https://github.com/policratus/pupyl
Author: Nelson Forte
Author-email: policratus@gmail.com
Classifier: Programming Language :: Python :: 3
Classifier: License :: OSI Approved :: GNU Lesser General Public License v3 (LGPLv3)
Classifier: Operating System :: OS Independent
Classifier: Development Status :: 5 - Production/Stable
Classifier: Programming Language :: Python :: 3.9
Classifier: Topic :: Scientific/Engineering :: Image Recognition
Requires-Python: >=3.9
License-File: LICENSE
Requires-Dist: tensorflow ==2.17.0
Requires-Dist: annoy ==1.17.3
